<?xml version="1.0" encoding="utf-8"?>
<SoundBanksInfo Platform="Mac" BasePlatform="Mac" SchemaVersion="11" SoundbankVersion="132">
	<RootPaths>
		<ProjectRoot>M:\The_Fall_New\The Fall\The Fall\The Fall_WwiseProject\</ProjectRoot>
		<SourceFilesRoot>M:\The_Fall_New\The Fall\The Fall\The Fall_WwiseProject\.cache\Mac\</SourceFilesRoot>
		<SoundBanksRoot>M:\The_Fall_New\The Fall\The Fall\The Fall_WwiseProject\GeneratedSoundBanks\Mac\</SoundBanksRoot>
		<ExternalSourcesInputFile></ExternalSourcesInputFile>
		<ExternalSourcesOutputRoot>M:\The_Fall_New\The Fall\The Fall\The Fall_WwiseProject\GeneratedSoundBanks\Mac</ExternalSourcesOutputRoot>
	</RootPaths>
	<DialogueEvents/>
	<StreamedFiles/>
	<MediaFilesNotInAnyBank/>
	<SoundBanks>
		<SoundBank Id="456359398" Language="SFX">
			<ObjectPath>\SoundBanks\Default Work Unit\TheFallMusic</ObjectPath>
			<ShortName>TheFallMusic</ShortName>
			<Path>TheFallMusic.bnk</Path>
			<IncludedEvents>
				<Event Id="1003497107" Name="Start_Menu_Music" ObjectPath="\Events\Default Work Unit\Music\Start_Menu_Music"/>
				<Event Id="540993415" Name="Start_Music" ObjectPath="\Events\Default Work Unit\Music\Start_Music"/>
				<Event Id="3945748993" Name="Stop_Menu_Music" ObjectPath="\Events\Default Work Unit\Music\Stop_Menu_Music"/>
				<Event Id="2837384057" Name="Stop_Music" ObjectPath="\Events\Default Work Unit\Music\Stop_Music"/>
			</IncludedEvents>
			<IncludedMemoryFiles>
				<File Id="47316527" Language="SFX">
					<ShortName>The_Fall_Music_A(Compressed).wav</ShortName>
					<Path>SFX\The_Fall_Music_A(Compressed)_CB1F3167.wem</Path>
				</File>
				<File Id="308222834" Language="SFX">
					<ShortName>The_Fall_Music_B_To_C.wav</ShortName>
					<Path>SFX\The_Fall_Music_B_To_C_CB1F3167.wem</Path>
				</File>
				<File Id="391436893" Language="SFX">
					<ShortName>The_Fall_Music_E_Compressed.wav</ShortName>
					<Path>SFX\The_Fall_Music_E_Compressed_CB1F3167.wem</Path>
				</File>
				<File Id="605108431" Language="SFX">
					<ShortName>The_Fall_Music_D(new)_Compressed.wav</ShortName>
					<Path>SFX\The_Fall_Music_D(new)_Compressed_CB1F3167.wem</Path>
				</File>
				<File Id="739456777" Language="SFX">
					<ShortName>The_Fall_Music_F_Compressed.wav</ShortName>
					<Path>SFX\The_Fall_Music_F_Compressed_CB1F3167.wem</Path>
				</File>
				<File Id="743589583" Language="SFX">
					<ShortName>The_Fall_Menu_(withTail).wav</ShortName>
					<Path>SFX\The_Fall_Menu_(withTail)_CB1F3167.wem</Path>
				</File>
				<File Id="968211500" Language="SFX">
					<ShortName>The_Fall_Music_C(new)4_Compressed.wav</ShortName>
					<Path>SFX\The_Fall_Music_C(new)4_Compressed_CB1F3167.wem</Path>
				</File>
				<File Id="1027916952" Language="SFX">
					<ShortName>The_Fall_Music_B(Compressed).wav</ShortName>
					<Path>SFX\The_Fall_Music_B(Compressed)_CB1F3167.wem</Path>
				</File>
			</IncludedMemoryFiles>
		</SoundBank>
		<SoundBank Id="787924302" Language="SFX">
			<ObjectPath>\SoundBanks\Default Work Unit\TheFallSFX</ObjectPath>
			<ShortName>TheFallSFX</ShortName>
			<Path>TheFallSFX.bnk</Path>
			<IncludedEvents>
				<Event Id="1571488543" Name="Aim_Error" ObjectPath="\Events\Default Work Unit\SFX\Ball\Aim_Error"/>
				<Event Id="938529747" Name="Menu_Button" ObjectPath="\Events\Default Work Unit\SFX\UI\Menu_Button"/>
				<Event Id="1286977679" Name="Play_Aiming" ObjectPath="\Events\Default Work Unit\SFX\Ball\Play_Aiming"/>
				<Event Id="1172822028" Name="Play_Death" ObjectPath="\Events\Default Work Unit\SFX\Ball\Play_Death"/>
				<Event Id="3691806113" Name="Play_Enter_Portal" ObjectPath="\Events\Default Work Unit\SFX\Ball\Play_Enter_Portal"/>
				<Event Id="2773446032" Name="Play_Goal_Reached" ObjectPath="\Events\Default Work Unit\SFX\Level_Elements\Play_Goal_Reached"/>
				<Event Id="2764105556" Name="Play_Impact" ObjectPath="\Events\Default Work Unit\SFX\Ball\Play_Impact"/>
				<Event Id="1357778998" Name="Play_Menu_Click" ObjectPath="\Events\Default Work Unit\SFX\UI\Play_Menu_Click"/>
				<Event Id="3771381609" Name="Play_Menu_Sting" ObjectPath="\Events\Default Work Unit\SFX\UI\Play_Menu_Sting"/>
				<Event Id="3483232275" Name="Play_Restart" ObjectPath="\Events\Default Work Unit\SFX\UI\Play_Restart"/>
				<Event Id="2641650631" Name="Play_Shoot" ObjectPath="\Events\Default Work Unit\SFX\Ball\Play_Shoot"/>
				<Event Id="1240630412" Name="Play_Trigger_Hit" ObjectPath="\Events\Default Work Unit\SFX\Level_Elements\Play_Trigger_Hit"/>
				<Event Id="1114964412" Name="Start_Game" ObjectPath="\Events\Default Work Unit\SFX\UI\Start_Game"/>
				<Event Id="3155875016" Name="Start_Goal_Static" ObjectPath="\Events\Default Work Unit\SFX\Level_Elements\Start_Goal_Static"/>
				<Event Id="1967504570" Name="Start_Opening_Anim" ObjectPath="\Events\Default Work Unit\SFX\Level_Elements\Start_Opening_Anim"/>
				<Event Id="3237166277" Name="Start_Portal_Static" ObjectPath="\Events\Default Work Unit\SFX\Level_Elements\Start_Portal_Static"/>
				<Event Id="3525056021" Name="Stop_Aiming" ObjectPath="\Events\Default Work Unit\SFX\Ball\Stop_Aiming"/>
				<Event Id="951397446" Name="Stop_Goal_Static" ObjectPath="\Events\Default Work Unit\SFX\Level_Elements\Stop_Goal_Static"/>
				<Event Id="1797269043" Name="Stop_Portal_Static" ObjectPath="\Events\Default Work Unit\SFX\Level_Elements\Stop_Portal_Static"/>
				<Event Id="1230525119" Name="Wall_Appear" ObjectPath="\Events\Default Work Unit\SFX\Level_Elements\Wall_Appear"/>
				<Event Id="2274397818" Name="Wall_Destroy" ObjectPath="\Events\Default Work Unit\SFX\Level_Elements\Wall_Destroy"/>
			</IncludedEvents>
			<IncludedMemoryFiles>
				<File Id="17111417" Language="SFX">
					<ShortName>High_ap_3.wav</ShortName>
					<Path>SFX\High_ap_3_3C9191CC.wem</Path>
				</File>
				<File Id="31632225" Language="SFX">
					<ShortName>Low1.wav</ShortName>
					<Path>SFX\Low1_5AE02759.wem</Path>
				</File>
				<File Id="44492403" Language="SFX">
					<ShortName>Metal4.wav</ShortName>
					<Path>SFX\Metal4_A1793BE9.wem</Path>
				</File>
				<File Id="46570503" Language="SFX">
					<ShortName>Note4.wav</ShortName>
					<Path>SFX\Note4_A1793BE9.wem</Path>
				</File>
				<File Id="52410626" Language="SFX">
					<ShortName>Flame3.wav</ShortName>
					<Path>SFX\Flame3_A1793BE9.wem</Path>
				</File>
				<File Id="53718916" Language="SFX">
					<ShortName>Fall_Menu1_Sting_BitCrushed_Faded.wav</ShortName>
					<Path>SFX\Fall_Menu1_Sting_BitCrushed_Faded_34BA8D23.wem</Path>
				</File>
				<File Id="88479568" Language="SFX">
					<ShortName>Voice2.wav</ShortName>
					<Path>SFX\Voice2_A1793BE9.wem</Path>
				</File>
				<File Id="88628497" Language="SFX">
					<ShortName>High_ap_2.wav</ShortName>
					<Path>SFX\High_ap_2_6277E291.wem</Path>
				</File>
				<File Id="95252519" Language="SFX">
					<ShortName>SFX\Trigger.wav</ShortName>
					<Path>SFX\SFX\Trigger_A1793BE9.wem</Path>
				</File>
				<File Id="112245833" Language="SFX">
					<ShortName>High_ap_1.wav</ShortName>
					<Path>SFX\High_ap_1_9748BF0C.wem</Path>
				</File>
				<File Id="156048466" Language="SFX">
					<ShortName>Glass4.wav</ShortName>
					<Path>SFX\Glass4_A1793BE9.wem</Path>
				</File>
				<File Id="157507196" Language="SFX">
					<ShortName>SFX\PortalConcept6.wav</ShortName>
					<Path>SFX\SFX\PortalConcept6_8A2CB1AA.wem</Path>
				</File>
				<File Id="161584208" Language="SFX">
					<ShortName>FallMainSting2-03.wav</ShortName>
					<Path>SFX\FallMainSting2-03_8A52C6E4.wem</Path>
				</File>
				<File Id="169300806" Language="SFX">
					<ShortName>SFX\UI_Click1.wav</ShortName>
					<Path>SFX\SFX\UI_Click1_0FC2F2EE.wem</Path>
				</File>
				<File Id="170259432" Language="SFX">
					<ShortName>Glass1.wav</ShortName>
					<Path>SFX\Glass1_7A401ADA.wem</Path>
				</File>
				<File Id="198501661" Language="SFX">
					<ShortName>SFX\PortalConcept6.wav</ShortName>
					<Path>SFX\SFX\PortalConcept6_A1793BE9.wem</Path>
				</File>
				<File Id="220571911" Language="SFX">
					<ShortName>High4.wav</ShortName>
					<Path>SFX\High4_A1793BE9.wem</Path>
				</File>
				<File Id="245469834" Language="SFX">
					<ShortName>Metal1.wav</ShortName>
					<Path>SFX\Metal1_A1793BE9.wem</Path>
				</File>
				<File Id="270967207" Language="SFX">
					<ShortName>SFX\Shoot3.wav</ShortName>
					<Path>SFX\SFX\Shoot3_A1793BE9.wem</Path>
				</File>
				<File Id="295408699" Language="SFX">
					<ShortName>SFX\Complete2-02.wav</ShortName>
					<Path>SFX\SFX\Complete2-02_A1793BE9.wem</Path>
				</File>
				<File Id="313218285" Language="SFX">
					<ShortName>Glass6.wav</ShortName>
					<Path>SFX\Glass6_A1793BE9.wem</Path>
				</File>
				<File Id="315634734" Language="SFX">
					<ShortName>Fire2.wav</ShortName>
					<Path>SFX\Fire2_94A25F2F.wem</Path>
				</File>
				<File Id="319476158" Language="SFX">
					<ShortName>thump1.wav</ShortName>
					<Path>SFX\thump1_A1793BE9.wem</Path>
				</File>
				<File Id="333960489" Language="SFX">
					<ShortName>High3.wav</ShortName>
					<Path>SFX\High3_A1793BE9.wem</Path>
				</File>
				<File Id="336421410" Language="SFX">
					<ShortName>thump3.wav</ShortName>
					<Path>SFX\thump3_A1793BE9.wem</Path>
				</File>
				<File Id="437261794" Language="SFX">
					<ShortName>Metal2.wav</ShortName>
					<Path>SFX\Metal2_A1793BE9.wem</Path>
				</File>
				<File Id="445375944" Language="SFX">
					<ShortName>Glass2.wav</ShortName>
					<Path>SFX\Glass2_D72B34AB.wem</Path>
				</File>
				<File Id="461551322" Language="SFX">
					<ShortName>Note3.wav</ShortName>
					<Path>SFX\Note3_A1793BE9.wem</Path>
				</File>
				<File Id="464154206" Language="SFX">
					<ShortName>thump5.wav</ShortName>
					<Path>SFX\thump5_A1793BE9.wem</Path>
				</File>
				<File Id="490400559" Language="SFX">
					<ShortName>Glass5.wav</ShortName>
					<Path>SFX\Glass5_A1793BE9.wem</Path>
				</File>
				<File Id="567623184" Language="SFX">
					<ShortName>Fire1.wav</ShortName>
					<Path>SFX\Fire1_EB3CCA00.wem</Path>
				</File>
				<File Id="595145526" Language="SFX">
					<ShortName>Glass7.wav</ShortName>
					<Path>SFX\Glass7_A1793BE9.wem</Path>
				</File>
				<File Id="624514289" Language="SFX">
					<ShortName>Low2.wav</ShortName>
					<Path>SFX\Low2_3F34108B.wem</Path>
				</File>
				<File Id="625828542" Language="SFX">
					<ShortName>Metal3.wav</ShortName>
					<Path>SFX\Metal3_A1793BE9.wem</Path>
				</File>
				<File Id="625982357" Language="SFX">
					<ShortName>Note2.wav</ShortName>
					<Path>SFX\Note2_A1793BE9.wem</Path>
				</File>
				<File Id="627389439" Language="SFX">
					<ShortName>SFX\AimSwellConcept.wav</ShortName>
					<Path>SFX\SFX\AimSwellConcept_CB1F3167.wem</Path>
				</File>
				<File Id="652943065" Language="SFX">
					<ShortName>Fire4.wav</ShortName>
					<Path>SFX\Fire4_446F0724.wem</Path>
				</File>
				<File Id="679780921" Language="SFX">
					<ShortName>Voice3.wav</ShortName>
					<Path>SFX\Voice3_A1793BE9.wem</Path>
				</File>
				<File Id="766326013" Language="SFX">
					<ShortName>High_ap_4.wav</ShortName>
					<Path>SFX\High_ap_4_BD7B803D.wem</Path>
				</File>
				<File Id="768982178" Language="SFX">
					<ShortName>Voice4.wav</ShortName>
					<Path>SFX\Voice4_A1793BE9.wem</Path>
				</File>
				<File Id="772585177" Language="SFX">
					<ShortName>Fire5.wav</ShortName>
					<Path>SFX\Fire5_E322843D.wem</Path>
				</File>
				<File Id="777279287" Language="SFX">
					<ShortName>Flame4.wav</ShortName>
					<Path>SFX\Flame4_A1793BE9.wem</Path>
				</File>
				<File Id="784611864" Language="SFX">
					<ShortName>Flame1.wav</ShortName>
					<Path>SFX\Flame1_A1793BE9.wem</Path>
				</File>
				<File Id="787069680" Language="SFX">
					<ShortName>High1.wav</ShortName>
					<Path>SFX\High1_A1793BE9.wem</Path>
				</File>
				<File Id="850005335" Language="SFX">
					<ShortName>Fire3.wav</ShortName>
					<Path>SFX\Fire3_D16E9E76.wem</Path>
				</File>
				<File Id="865166560" Language="SFX">
					<ShortName>Low4.wav</ShortName>
					<Path>SFX\Low4_4B188091.wem</Path>
				</File>
				<File Id="870579763" Language="SFX">
					<ShortName>SFX\UI_Click2.wav</ShortName>
					<Path>SFX\SFX\UI_Click2_4A54C122.wem</Path>
				</File>
				<File Id="893859057" Language="SFX">
					<ShortName>thump2.wav</ShortName>
					<Path>SFX\thump2_A1793BE9.wem</Path>
				</File>
				<File Id="896999008" Language="SFX">
					<ShortName>High2.wav</ShortName>
					<Path>SFX\High2_A1793BE9.wem</Path>
				</File>
				<File Id="927733360" Language="SFX">
					<ShortName>Low3.wav</ShortName>
					<Path>SFX\Low3_9EA60D2A.wem</Path>
				</File>
				<File Id="928577004" Language="SFX">
					<ShortName>thump4.wav</ShortName>
					<Path>SFX\thump4_A1793BE9.wem</Path>
				</File>
				<File Id="965128274" Language="SFX">
					<ShortName>Note1.wav</ShortName>
					<Path>SFX\Note1_A1793BE9.wem</Path>
				</File>
				<File Id="969934671" Language="SFX">
					<ShortName>Flame2.wav</ShortName>
					<Path>SFX\Flame2_A1793BE9.wem</Path>
				</File>
				<File Id="971122452" Language="SFX">
					<ShortName>Glass9.wav</ShortName>
					<Path>SFX\Glass9_A1793BE9.wem</Path>
				</File>
				<File Id="977109968" Language="SFX">
					<ShortName>Voice1.wav</ShortName>
					<Path>SFX\Voice1_A1793BE9.wem</Path>
				</File>
				<File Id="993902946" Language="SFX">
					<ShortName>SFX\UI_hover.wav</ShortName>
					<Path>SFX\SFX\UI_hover_36072B27.wem</Path>
				</File>
				<File Id="1020489139" Language="SFX">
					<ShortName>38 Track 38.wav</ShortName>
					<Path>SFX\38 Track 38_8F244C66.wem</Path>
				</File>
				<File Id="1021680210" Language="SFX">
					<ShortName>Glass3.wav</ShortName>
					<Path>SFX\Glass3_A1793BE9.wem</Path>
				</File>
				<File Id="1057195292" Language="SFX">
					<ShortName>PortalStatic1.wav</ShortName>
					<Path>SFX\PortalStatic1_112CA0E5.wem</Path>
				</File>
				<File Id="1063548857" Language="SFX">
					<ShortName>GoalStatic.wav</ShortName>
					<Path>SFX\GoalStatic_C75A19BD.wem</Path>
				</File>
			</IncludedMemoryFiles>
		</SoundBank>
		<SoundBank Id="1355168291" Language="SFX">
			<ObjectPath>Init</ObjectPath>
			<ShortName>Init</ShortName>
			<Path>Init.bnk</Path>
		</SoundBank>
		<SoundBank Id="3496721321" Language="SFX">
			<ObjectPath>\SoundBanks\Default Work Unit\FallNarrator</ObjectPath>
			<ShortName>FallNarrator</ShortName>
			<Path>FallNarrator.bnk</Path>
			<IncludedEvents>
				<Event Id="2187083841" Name="Narrator_Compliment" ObjectPath="\Events\Default Work Unit\Narrator\Narrator_Compliment"/>
				<Event Id="1035940725" Name="Narrator_Death" ObjectPath="\Events\Default Work Unit\Narrator\Narrator_Death"/>
				<Event Id="4022731410" Name="Narrator_Greeting_Generic" ObjectPath="\Events\Default Work Unit\Narrator\Narrator_Greeting_Generic"/>
				<Event Id="1028928662" Name="Narrator_Impatience" ObjectPath="\Events\Default Work Unit\Narrator\Narrator_Impatience"/>
				<Event Id="3847834209" Name="Narrator_Tut1_1" ObjectPath="\Events\Default Work Unit\Narrator\Narrator_Tut1_1"/>
				<Event Id="3847834210" Name="Narrator_Tut1_2" ObjectPath="\Events\Default Work Unit\Narrator\Narrator_Tut1_2"/>
				<Event Id="3847834211" Name="Narrator_Tut1_3" ObjectPath="\Events\Default Work Unit\Narrator\Narrator_Tut1_3"/>
				<Event Id="3847834212" Name="Narrator_Tut1_4" ObjectPath="\Events\Default Work Unit\Narrator\Narrator_Tut1_4"/>
				<Event Id="3847834213" Name="Narrator_Tut1_5" ObjectPath="\Events\Default Work Unit\Narrator\Narrator_Tut1_5"/>
				<Event Id="3847834214" Name="Narrator_Tut1_6" ObjectPath="\Events\Default Work Unit\Narrator\Narrator_Tut1_6"/>
				<Event Id="3847834215" Name="Narrator_Tut1_7" ObjectPath="\Events\Default Work Unit\Narrator\Narrator_Tut1_7"/>
				<Event Id="3847834216" Name="Narrator_Tut1_8" ObjectPath="\Events\Default Work Unit\Narrator\Narrator_Tut1_8"/>
				<Event Id="327987379" Name="Narrator_Tut_2" ObjectPath="\Events\Default Work Unit\Narrator\Narrator_Tut_2"/>
				<Event Id="327987378" Name="Narrator_Tut_3" ObjectPath="\Events\Default Work Unit\Narrator\Narrator_Tut_3"/>
			</IncludedEvents>
			<IncludedMemoryFiles>
				<File Id="27954089" Language="SFX">
					<ShortName>Greet_Dis_3.wav</ShortName>
					<Path>SFX\Greet_Dis_3_63699958.wem</Path>
				</File>
				<File Id="30143869" Language="SFX">
					<ShortName>Welcome_2.wav</ShortName>
					<Path>SFX\Welcome_2_40183A52.wem</Path>
				</File>
				<File Id="65798351" Language="SFX">
					<ShortName>Hmm.wav</ShortName>
					<Path>SFX\Hmm_3CC5CA41.wem</Path>
				</File>
				<File Id="68563977" Language="SFX">
					<ShortName>Imp_VD_3.wav</ShortName>
					<Path>SFX\Imp_VD_3_6A430329.wem</Path>
				</File>
				<File Id="73176215" Language="SFX">
					<ShortName>Death_Neu_4.wav</ShortName>
					<Path>SFX\Death_Neu_4_564BEC25.wem</Path>
				</File>
				<File Id="73242151" Language="SFX">
					<ShortName>Greet_Hpy_1.wav</ShortName>
					<Path>SFX\Greet_Hpy_1_67B3CDDF.wem</Path>
				</File>
				<File Id="80214999" Language="SFX">
					<ShortName>Oh_Dear2.wav</ShortName>
					<Path>SFX\Oh_Dear2_C7FAE68F.wem</Path>
				</File>
				<File Id="83710978" Language="SFX">
					<ShortName>Death_H_4.wav</ShortName>
					<Path>SFX\Death_H_4_A1793BE9.wem</Path>
				</File>
				<File Id="90774846" Language="SFX">
					<ShortName>Congratz_VD_4(2).wav</ShortName>
					<Path>SFX\Congratz_VD_4(2)_D9B6F87D.wem</Path>
				</File>
				<File Id="93295401" Language="SFX">
					<ShortName>Imp_VD_1(2).wav</ShortName>
					<Path>SFX\Imp_VD_1(2)_87620F63.wem</Path>
				</File>
				<File Id="104463917" Language="SFX">
					<ShortName>Greetings_VD_2.wav</ShortName>
					<Path>SFX\Greetings_VD_2_D3F280F2.wem</Path>
				</File>
				<File Id="123125061" Language="SFX">
					<ShortName>Congratz_VH_3.wav</ShortName>
					<Path>SFX\Congratz_VH_3_B7152177.wem</Path>
				</File>
				<File Id="135655404" Language="SFX">
					<ShortName>Congratz_H_5.wav</ShortName>
					<Path>SFX\Congratz_H_5_81A9A295.wem</Path>
				</File>
				<File Id="145666830" Language="SFX">
					<ShortName>Greet_Hpy_3.wav</ShortName>
					<Path>SFX\Greet_Hpy_3_66790BB7.wem</Path>
				</File>
				<File Id="168345899" Language="SFX">
					<ShortName>Imp_Dis_3.wav</ShortName>
					<Path>SFX\Imp_Dis_3_56C357AB.wem</Path>
				</File>
				<File Id="175658029" Language="SFX">
					<ShortName>Greetings_VD_3.wav</ShortName>
					<Path>SFX\Greetings_VD_3_91389E8D.wem</Path>
				</File>
				<File Id="185383829" Language="SFX">
					<ShortName>Imp_VD_5.wav</ShortName>
					<Path>SFX\Imp_VD_5_72364AA1.wem</Path>
				</File>
				<File Id="195477368" Language="SFX">
					<ShortName>Imp_Dis_1.wav</ShortName>
					<Path>SFX\Imp_Dis_1_C3843BF5.wem</Path>
				</File>
				<File Id="203561363" Language="SFX">
					<ShortName>Greetings_VH_2.wav</ShortName>
					<Path>SFX\Greetings_VH_2_F7A2C4BF.wem</Path>
				</File>
				<File Id="218166800" Language="SFX">
					<ShortName>Congratz_Dis_2.wav</ShortName>
					<Path>SFX\Congratz_Dis_2_4E8A4655.wem</Path>
				</File>
				<File Id="240196402" Language="SFX">
					<ShortName>Greetings_VD_1.wav</ShortName>
					<Path>SFX\Greetings_VD_1_6E44D755.wem</Path>
				</File>
				<File Id="245392080" Language="SFX">
					<ShortName>Congratz_H_1.wav</ShortName>
					<Path>SFX\Congratz_H_1_9963E6F6.wem</Path>
				</File>
				<File Id="246904871" Language="SFX">
					<ShortName>Drag.wav</ShortName>
					<Path>SFX\Drag_A1793BE9.wem</Path>
				</File>
				<File Id="251089787" Language="SFX">
					<ShortName>Death_VD_6.wav</ShortName>
					<Path>SFX\Death_VD_6_CBAC2EF2.wem</Path>
				</File>
				<File Id="255677979" Language="SFX">
					<ShortName>Greet_Dis_1.wav</ShortName>
					<Path>SFX\Greet_Dis_1_76EFC298.wem</Path>
				</File>
				<File Id="272615380" Language="SFX">
					<ShortName>Death_VH_5.wav</ShortName>
					<Path>SFX\Death_VH_5_CD4E3587.wem</Path>
				</File>
				<File Id="278173825" Language="SFX">
					<ShortName>Greet_Nu_1.wav</ShortName>
					<Path>SFX\Greet_Nu_1_12EC2696.wem</Path>
				</File>
				<File Id="290839033" Language="SFX">
					<ShortName>Congratz_Neu_2.wav</ShortName>
					<Path>SFX\Congratz_Neu_2_102F14DC.wem</Path>
				</File>
				<File Id="320354256" Language="SFX">
					<ShortName>Death_VD_4.wav</ShortName>
					<Path>SFX\Death_VD_4_D31E65C9.wem</Path>
				</File>
				<File Id="327769538" Language="SFX">
					<ShortName>Death_VH_3.wav</ShortName>
					<Path>SFX\Death_VH_3_1142182F.wem</Path>
				</File>
				<File Id="333730461" Language="SFX">
					<ShortName>Death_VD_5.wav</ShortName>
					<Path>SFX\Death_VD_5_56645621.wem</Path>
				</File>
				<File Id="355686734" Language="SFX">
					<ShortName>Greetings_VH_3.wav</ShortName>
					<Path>SFX\Greetings_VH_3_AAACE960.wem</Path>
				</File>
				<File Id="378302267" Language="SFX">
					<ShortName>Greet_Nu_3.wav</ShortName>
					<Path>SFX\Greet_Nu_3_C8DE24C5.wem</Path>
				</File>
				<File Id="383385249" Language="SFX">
					<ShortName>Imp_Dis_4.wav</ShortName>
					<Path>SFX\Imp_Dis_4_A1793BE9.wem</Path>
				</File>
				<File Id="386772719" Language="SFX">
					<ShortName>Imp_VH_3.wav</ShortName>
					<Path>SFX\Imp_VH_3_2F2BFE1C.wem</Path>
				</File>
				<File Id="397044146" Language="SFX">
					<ShortName>New_Ooh_Portals.wav</ShortName>
					<Path>SFX\New_Ooh_Portals_1141EBC3.wem</Path>
				</File>
				<File Id="406144920" Language="SFX">
					<ShortName>Lets_Start.wav</ShortName>
					<Path>SFX\Lets_Start_A1793BE9.wem</Path>
				</File>
				<File Id="416477332" Language="SFX">
					<ShortName>Congratz_Neu_1.wav</ShortName>
					<Path>SFX\Congratz_Neu_1_477DD68B.wem</Path>
				</File>
				<File Id="416873939" Language="SFX">
					<ShortName>Congratz_Neu_5.wav</ShortName>
					<Path>SFX\Congratz_Neu_5_79900018.wem</Path>
				</File>
				<File Id="418949962" Language="SFX">
					<ShortName>Asked_Too_Much2.wav</ShortName>
					<Path>SFX\Asked_Too_Much2_363C8EB0.wem</Path>
				</File>
				<File Id="425245753" Language="SFX">
					<ShortName>Greet_Dis_2.wav</ShortName>
					<Path>SFX\Greet_Dis_2_D17BBABC.wem</Path>
				</File>
				<File Id="467938584" Language="SFX">
					<ShortName>Congratz_VD_5.wav</ShortName>
					<Path>SFX\Congratz_VD_5_5D99753C.wem</Path>
				</File>
				<File Id="478118920" Language="SFX">
					<ShortName>To_Shoot2.wav</ShortName>
					<Path>SFX\To_Shoot2_89D4997A.wem</Path>
				</File>
				<File Id="500451625" Language="SFX">
					<ShortName>Congratz_VH_5.wav</ShortName>
					<Path>SFX\Congratz_VH_5_8939185C.wem</Path>
				</File>
				<File Id="517610230" Language="SFX">
					<ShortName>Imp_Nu_2.wav</ShortName>
					<Path>SFX\Imp_Nu_2_D89657C3.wem</Path>
				</File>
				<File Id="518692454" Language="SFX">
					<ShortName>Death_Neu_6.wav</ShortName>
					<Path>SFX\Death_Neu_6_E79F6D51.wem</Path>
				</File>
				<File Id="546691221" Language="SFX">
					<ShortName>Death_VD_1.wav</ShortName>
					<Path>SFX\Death_VD_1_3E675D3B.wem</Path>
				</File>
				<File Id="556136457" Language="SFX">
					<ShortName>Imp_Hpy_1.wav</ShortName>
					<Path>SFX\Imp_Hpy_1_6D736433.wem</Path>
				</File>
				<File Id="556457294" Language="SFX">
					<ShortName>Death_Dis_5.wav</ShortName>
					<Path>SFX\Death_Dis_5_A1793BE9.wem</Path>
				</File>
				<File Id="561932729" Language="SFX">
					<ShortName>Congratz_VD_2.wav</ShortName>
					<Path>SFX\Congratz_VD_2_ADFB0D41.wem</Path>
				</File>
				<File Id="577875518" Language="SFX">
					<ShortName>Congratz_Dis_3.wav</ShortName>
					<Path>SFX\Congratz_Dis_3_FAA62323.wem</Path>
				</File>
				<File Id="578953221" Language="SFX">
					<ShortName>Imp_VD_4.wav</ShortName>
					<Path>SFX\Imp_VD_4_19C451FE.wem</Path>
				</File>
				<File Id="583770870" Language="SFX">
					<ShortName>Congratz_VH_2.wav</ShortName>
					<Path>SFX\Congratz_VH_2_6D1EBBB0.wem</Path>
				</File>
				<File Id="586415068" Language="SFX">
					<ShortName>Imp_Nu_4.wav</ShortName>
					<Path>SFX\Imp_Nu_4_B5A00A9C.wem</Path>
				</File>
				<File Id="609100086" Language="SFX">
					<ShortName>Congratz_VH_4.wav</ShortName>
					<Path>SFX\Congratz_VH_4_904A31D5.wem</Path>
				</File>
				<File Id="613675443" Language="SFX">
					<ShortName>Death_Dis_4.wav</ShortName>
					<Path>SFX\Death_Dis_4_8387C0B4.wem</Path>
				</File>
				<File Id="634742679" Language="SFX">
					<ShortName>Death_VH_2.wav</ShortName>
					<Path>SFX\Death_VH_2_2C855CA0.wem</Path>
				</File>
				<File Id="640566069" Language="SFX">
					<ShortName>Imp_VD_2(Bleeped).wav</ShortName>
					<Path>SFX\Imp_VD_2(Bleeped)_4C6BB23F.wem</Path>
				</File>
				<File Id="640627932" Language="SFX">
					<ShortName>Death_H_5.wav</ShortName>
					<Path>SFX\Death_H_5_A1793BE9.wem</Path>
				</File>
				<File Id="645943349" Language="SFX">
					<ShortName>Retry.wav</ShortName>
					<Path>SFX\Retry_0F2BC61E.wem</Path>
				</File>
				<File Id="647762667" Language="SFX">
					<ShortName>I'm_Sure.wav</ShortName>
					<Path>SFX\I'm_Sure_CFB927B7.wem</Path>
				</File>
				<File Id="648586546" Language="SFX">
					<ShortName>Imp_Hpy_3.wav</ShortName>
					<Path>SFX\Imp_Hpy_3_A52CF814.wem</Path>
				</File>
				<File Id="651664379" Language="SFX">
					<ShortName>Congratz_Dis_1.wav</ShortName>
					<Path>SFX\Congratz_Dis_1_E235DCD7.wem</Path>
				</File>
				<File Id="655771658" Language="SFX">
					<ShortName>Congratz_Neu_4.wav</ShortName>
					<Path>SFX\Congratz_Neu_4_EB9B2427.wem</Path>
				</File>
				<File Id="664591045" Language="SFX">
					<ShortName>Imp_VH_4.wav</ShortName>
					<Path>SFX\Imp_VH_4_CFA78882.wem</Path>
				</File>
				<File Id="676836335" Language="SFX">
					<ShortName>Imp_Nu_3.wav</ShortName>
					<Path>SFX\Imp_Nu_3_863160A2.wem</Path>
				</File>
				<File Id="680595730" Language="SFX">
					<ShortName>This_Objective.wav</ShortName>
					<Path>SFX\This_Objective_A1793BE9.wem</Path>
				</File>
				<File Id="689279227" Language="SFX">
					<ShortName>Congratz_VD_3.wav</ShortName>
					<Path>SFX\Congratz_VD_3_D68267AB.wem</Path>
				</File>
				<File Id="693208066" Language="SFX">
					<ShortName>Greetings_VH_1.wav</ShortName>
					<Path>SFX\Greetings_VH_1_69190412.wem</Path>
				</File>
				<File Id="696077823" Language="SFX">
					<ShortName>Congratz_H_4.wav</ShortName>
					<Path>SFX\Congratz_H_4_A9101750.wem</Path>
				</File>
				<File Id="705212636" Language="SFX">
					<ShortName>Imp_VH_1.wav</ShortName>
					<Path>SFX\Imp_VH_1_9227775A.wem</Path>
				</File>
				<File Id="708777935" Language="SFX">
					<ShortName>Interesting2.wav</ShortName>
					<Path>SFX\Interesting2_606F0A50.wem</Path>
				</File>
				<File Id="724764249" Language="SFX">
					<ShortName>Congratz_H_2.wav</ShortName>
					<Path>SFX\Congratz_H_2_D257FF7F.wem</Path>
				</File>
				<File Id="732447586" Language="SFX">
					<ShortName>BOunce_2.wav</ShortName>
					<Path>SFX\BOunce_2_564EF1BF.wem</Path>
				</File>
				<File Id="772457920" Language="SFX">
					<ShortName>Imp_Neu_4.wav</ShortName>
					<Path>SFX\Imp_Neu_4_CB9F7488.wem</Path>
				</File>
				<File Id="772477979" Language="SFX">
					<ShortName>Imp_VH_2.wav</ShortName>
					<Path>SFX\Imp_VH_2_F0CFB0C1.wem</Path>
				</File>
				<File Id="801848853" Language="SFX">
					<ShortName>Death_Neu_5.wav</ShortName>
					<Path>SFX\Death_Neu_5_212642C9.wem</Path>
				</File>
				<File Id="815610686" Language="SFX">
					<ShortName>Imp_Hpy_5.wav</ShortName>
					<Path>SFX\Imp_Hpy_5_1B4EB655.wem</Path>
				</File>
				<File Id="816312119" Language="SFX">
					<ShortName>New_Moving_Obj.wav</ShortName>
					<Path>SFX\New_Moving_Obj_140A5CD4.wem</Path>
				</File>
				<File Id="818367716" Language="SFX">
					<ShortName>Congratz_Dis_4.wav</ShortName>
					<Path>SFX\Congratz_Dis_4_D1919761.wem</Path>
				</File>
				<File Id="847602493" Language="SFX">
					<ShortName>Really_2.wav</ShortName>
					<Path>SFX\Really_2_7CFBBF0E.wem</Path>
				</File>
				<File Id="853164434" Language="SFX">
					<ShortName>Imp_Hpy_4.wav</ShortName>
					<Path>SFX\Imp_Hpy_4_53C2E21E.wem</Path>
				</File>
				<File Id="857540524" Language="SFX">
					<ShortName>Congratz_VD_1.wav</ShortName>
					<Path>SFX\Congratz_VD_1_F5B8F3D9.wem</Path>
				</File>
				<File Id="861940552" Language="SFX">
					<ShortName>Death_Hpy_6.wav</ShortName>
					<Path>SFX\Death_Hpy_6_A1793BE9.wem</Path>
				</File>
				<File Id="869482296" Language="SFX">
					<ShortName>Death_VD_3.wav</ShortName>
					<Path>SFX\Death_VD_3_A1793BE9.wem</Path>
				</File>
				<File Id="904679458" Language="SFX">
					<ShortName>Congratz_H_3.wav</ShortName>
					<Path>SFX\Congratz_H_3_7974B71B.wem</Path>
				</File>
				<File Id="919381078" Language="SFX">
					<ShortName>Pause.wav</ShortName>
					<Path>SFX\Pause_A1793BE9.wem</Path>
				</File>
				<File Id="928924918" Language="SFX">
					<ShortName>Imp_Dis_2.wav</ShortName>
					<Path>SFX\Imp_Dis_2_E68C216B.wem</Path>
				</File>
				<File Id="937534766" Language="SFX">
					<ShortName>Congratz_VH_1.wav</ShortName>
					<Path>SFX\Congratz_VH_1_91EDF3DD.wem</Path>
				</File>
				<File Id="944949560" Language="SFX">
					<ShortName>Death_VH_4.wav</ShortName>
					<Path>SFX\Death_VH_4_F5EAD33B.wem</Path>
				</File>
				<File Id="970109741" Language="SFX">
					<ShortName>Death_VD_2.wav</ShortName>
					<Path>SFX\Death_VD_2_6470C9CD.wem</Path>
				</File>
				<File Id="975986801" Language="SFX">
					<ShortName>Death_VH_1.wav</ShortName>
					<Path>SFX\Death_VH_1_EB9091AB.wem</Path>
				</File>
				<File Id="1024744969" Language="SFX">
					<ShortName>Sing2.wav</ShortName>
					<Path>SFX\Sing2_1D955858.wem</Path>
				</File>
				<File Id="1036444360" Language="SFX">
					<ShortName>Admire.wav</ShortName>
					<Path>SFX\Admire_CC1E90F5.wem</Path>
				</File>
				<File Id="1039503267" Language="SFX">
					<ShortName>C'mon.wav</ShortName>
					<Path>SFX\C'mon_C086B3B0.wem</Path>
				</File>
				<File Id="1058425099" Language="SFX">
					<ShortName>Congratz_Neu_3.wav</ShortName>
					<Path>SFX\Congratz_Neu_3_887CCC88.wem</Path>
				</File>
				<File Id="1058882495" Language="SFX">
					<ShortName>Greet_Nu_5.wav</ShortName>
					<Path>SFX\Greet_Nu_5_77F7702E.wem</Path>
				</File>
				<File Id="1067885850" Language="SFX">
					<ShortName>Greet_Hpy_5.wav</ShortName>
					<Path>SFX\Greet_Hpy_5_9B5E19A1.wem</Path>
				</File>
			</IncludedMemoryFiles>
		</SoundBank>
	</SoundBanks>
</SoundBanksInfo>
